Aglyph-3.0.0.post1.dist-info/METADATA
Aglyph-3.0.0.post1.dist-info/RECORD
Aglyph-3.0.0.post1.dist-info/WHEEL
Aglyph-3.0.0.post1.dist-info/top_level.txt
aglyph/__init__.py
aglyph/_compat.py
aglyph/assembler.py
aglyph/component.py
aglyph/context.py
aglyph/integration/__init__.py
aglyph/integration/cherrypy.py
